{
    "welcome": "Walpy වෙත සාදරයෙන් පිළිගනිමු!",
    "welcome_message": "ඔබගේ දුරකථනය සඳහා නොමිලේ බිතුපත් දහස් ගණනක් බ්‍රවුස් කර ඔබට අවශ්‍ය විටෙක ඒවා ඔබගේ අගුළු තිරය හෝ මුල් තිරය ලෙස සකසන්න.",
    "google_signin": "Google සමඟින් පුරනය වන්න",
    "next": "ඊළඟ",
    "walpy_day": "දවසේ වල්පි",
    "popular_walpys": "ජනප්‍රිය walpys",
    "new_walpys": "නව වල්පිස්",
    "items": {
        "categories": "වර්ග",
        "explore": "ගවේෂණය කරන්න",
        "favourites": "ප්රියතම",
        "about_the_app": "යෙදුම ගැන",
        "rate_app": "යෙදුම ශ්‍රේණිගත කරන්න",
        "change_language": "භාෂාව වෙනස් කරන්න"
    },
    "developed": "ඇලෙක්ලා",
    "configuration": "මුල් පිටුව සහ අගුළු තිරය සැකසීම:",
    "set_wallpaper": "බිතුපතක් ලෙස සකසන්න හෝ බාගන්න",
    "set": "බිතුපතක් ලෙස සකසන්න",
    "download": "බාගත",
    "set_lockscreen": "අගුළු තිරය ලෙස සකසන්න",
    "set_as": "As සකසන්න",
    "set_homescreen": "මුල් තිරය ලෙස සකසන්න",
    "set_both": "දෙකම ලෙස සකසන්න",
    "cancel": "අවලංගු කරන්න",
    "setting_lockscreen": "ඔබගේ අගුළු තිරය සැකසීම",
    "logout_confirm": "ඔබට ඇත්තටම ලොග්අවුට් කිරීමට අවශ්‍යද?",
    "close": "වසන්න",
    "supported_languages": {
        "spanish": "ස්පාඤ්ඤ",
        "english": "ඉංග්රීසි"
    },
    "signin_message": "ඔබ දැනටමත් පුරනය වී ඇත",
    "success_message": "හරි, තේරුණා",
    "open_config": "වින්‍යාසය විවෘත කරන්න",
    "complete_download": "බාගත කිරීම සම්පූර්ණයි!",
    "check_status_bar": "තත්ත්ව තීරුව පරීක්ෂා කරන්න",
    "permisson": "බාගත කිරීමට ගබඩා අවසරය ලබා දෙන්න",
    "allow_storage": "මෙම යෙදුම සඳහා ඕනෑම බිතුපතක් බාගත කිරීමට ඔබ ගබඩා අවසරය ලබා දිය යුතුය",
    "complete": "සම්පූර්ණයි",
    "setting_home_screen": "ඔබගේ මුල් තිරය සැකසීම",
    "progress": "ප්රගතිය:",
    "check_internet": "ඔබගේ අන්තර්ජාල සම්බන්ධතාවය පරීක්ෂා කරන්න!",
    "ios_support": "Ios සඳහා සහය නොදක්වයි",
    "progress_finished": "මුල් පිටුව සහ අගුළු තිරය සාර්ථකව සකසා ඇත"
}