{
    "welcome": "Բարի գալուստ walpy:",
    "welcome_message": "Զննեք հազարավոր անվճար պաստառներ ձեր հեռախոսի համար և դրեք դրանք որպես ձեր կողպեք էկրան կամ հիմնական էկրան, երբ ցանկանաք:",
    "google_signin": "Մուտք գործեք google-ով",
    "next": "Հաջորդը",
    "walpy_day": "Օրվա վալպին",
    "popular_walpys": "Հանրաճանաչ walpys",
    "new_walpys": "Նոր walpys",
    "items": {
        "categories": "Կատեգորիաներ",
        "explore": "Հետազոտել",
        "favourites": "Ֆավորիտներ",
        "about_the_app": "Հավելվածի մասին",
        "rate_app": "Գնահատեք հավելվածը",
        "change_language": "Փոխեք լեզուն"
    },
    "developed": "Ալեքլա",
    "configuration": "Հիմնական և կողպէկրանի կարգավորում.",
    "set_wallpaper": "Սահմանել որպես պաստառ կամ ներբեռնել",
    "set": "Սահմանել որպես պաստառ",
    "download": "Բեռնել",
    "set_lockscreen": "Սահմանել որպես կողպէկրան",
    "set_as": "Սահմանվում է",
    "set_homescreen": "Սահմանել որպես հիմնական էկրան",
    "set_both": "Սահմանել որպես երկուսն էլ",
    "cancel": "Չեղարկել",
    "setting_lockscreen": "Ձեր կողպէկրանի կարգավորումը",
    "logout_confirm": "Իսկապե՞ս ուզում եք դուրս գալ:",
    "close": "Փակել",
    "supported_languages": {
        "spanish": "Իսպաներեն",
        "english": "Անգլերեն"
    },
    "signin_message": "Դուք արդեն մուտք եք գործել",
    "success_message": "Լավ, հասկացա",
    "open_config": "Բացեք կոնֆիգուրացիան",
    "complete_download": "Ներբեռնումն ավարտված է:",
    "check_status_bar": "Ստուգեք կարգավիճակի բարը",
    "permisson": "Տրամադրել պահեստավորման թույլտվություն՝ ներբեռնելու համար",
    "allow_storage": "Այս հավելվածի ցանկացած պաստառ ներբեռնելու համար դուք պետք է թույլատրեք պահեստավորման թույլտվություն",
    "complete": "Ամբողջական",
    "setting_home_screen": "Ձեր հիմնական էկրանի կարգավորումը",
    "progress": "Առաջընթաց:",
    "check_internet": "Ստուգեք ձեր ինտերնետ կապը:",
    "ios_support": "Ios-ը չի աջակցվում",
    "progress_finished": "Գլխավոր և կողպէկրանը հաջողությամբ դրվեցին"
}